[
  {
    "key": 1089244901,
    "datasetKey": "ca7f81ae-ebf9-43a8-947c-535a87fe5aec",
    "publishingOrgKey": "4d653db1-17d5-4565-99a5-d88643e240ce",
    "networkKeys": [],
    "installationKey": "b38ff2b7-c8af-454e-b5af-ee760f0d5bca",
    "publishingCountry": "BR",
    "protocol": "DWC_ARCHIVE",
    "lastCrawled": "2018-09-24T19:20:37.563+0000",
    "lastParsed": "2018-09-24T19:20:37.659+0000",
    "crawlId": 118,
    "extensions": {},
    "basisOfRecord": "PRESERVED_SPECIMEN",
    "taxonKey": 4068217,
    "kingdomKey": 6,
    "phylumKey": 7707728,
    "classKey": 220,
    "orderKey": 7226464,
    "familyKey": 4930387,
    "genusKey": 2925766,
    "speciesKey": 7461943,
    "scientificName": "Heliophytum elongatum (Willd. ex Cham.) DC.",
    "kingdom": "Plantae",
    "phylum": "Tracheophyta",
    "order": "Boraginales",
    "family": "Heliotropiaceae",
    "genus": "Heliotropium",
    "species": "Heliotropium elongatum",
    "genericName": "Heliophytum",
    "specificEpithet": "elongatum",
    "taxonRank": "SPECIES",
    "dateIdentified": "2006-04-18T00:00:00.000+0000",
    "decimalLongitude": 0,
    "decimalLatitude": 0,
    "continent": "SOUTH_AMERICA",
    "stateProvince": "Cear\u00e1",
    "year": 2005,
    "month": 2,
    "day": 28,
    "eventDate": "2005-02-28T00:00:00.000+0000",
    "issues": [
      "ZERO_COORDINATE",
      "GEODETIC_DATUM_ASSUMED_WGS84",
      "COUNTRY_COORDINATE_MISMATCH"
    ],
    "lastInterpreted": "2018-09-24T19:20:38.962+0000",
    "license": "http://creativecommons.org/licenses/by-nc/4.0/legalcode",
    "identifiers": [],
    "facts": [],
    "relations": [],
    "geodeticDatum": "WGS84",
    "class": "Magnoliopsida",
    "countryCode": "BR",
    "country": "Brazil",
    "rightsHolder": "EAC - Herb\u00e1rio Prisco Bezerra",
    "identifier": "BRA:UFC:EAC:0000038955",
    "recordNumber": "s.n.",
    "datasetName": "EAC - Herb\u00e1rio Prisco Bezerra",
    "municipality": "Sobral",
    "locality": "Fazenda Uva.",
    "gbifID": "1089244901",
    "language": "pt",
    "collectionCode": "EAC",
    "occurrenceID": "BRA:UFC:EAC:0000038955",
    "type": "Collection",
    "catalogNumber": "38955",
    "recordedBy": "Alves, J.E.",
    "institutionCode": "Universidade Federal do Cear\u00e1, UFC",
    "ownerInstitutionCode": "Universidade Federal do Cear\u00e1, UFC",
    "occurrenceRemarks": "flora 07, flor branca",
    "identifiedBy": "Nunes, E.",
    "_datasetKey": {
      "title": "EAC - Herb\u00e1rio Prisco Bezerra"
    },
    "_publishingOrgKey": {
      "title": "Universidade Federal do Cear\u00e1"
    },
    "_verbatimRecord": {
      "http://rs.tdwg.org/dwc/terms/scientificName": "Heliophytum elongatum"
    }
  },
  {
    "key": 1094175434,
    "datasetKey": "fffdea53-c113-4cdc-896e-a9c5fd726591",
    "publishingOrgKey": "1c72778c-05de-4f31-b83a-ff541ce5dff7",
    "networkKeys": [],
    "installationKey": "b38ff2b7-c8af-454e-b5af-ee760f0d5bca",
    "publishingCountry": "BR",
    "protocol": "DWC_ARCHIVE",
    "lastCrawled": "2018-09-25T15:14:28.527+0000",
    "lastParsed": "2018-09-25T15:14:28.530+0000",
    "crawlId": 72,
    "extensions": {},
    "basisOfRecord": "PRESERVED_SPECIMEN",
    "taxonKey": 7461943,
    "kingdomKey": 6,
    "phylumKey": 7707728,
    "classKey": 220,
    "orderKey": 7226464,
    "familyKey": 4930387,
    "genusKey": 2925766,
    "speciesKey": 7461943,
    "scientificName": "Heliotropium elongatum Willd. ex Cham.",
    "kingdom": "Plantae",
    "phylum": "Tracheophyta",
    "order": "Boraginales",
    "family": "Heliotropiaceae",
    "genus": "Heliotropium",
    "species": "Heliotropium elongatum",
    "genericName": "Heliotropium",
    "specificEpithet": "elongatum",
    "taxonRank": "SPECIES",
    "decimalLongitude": -39.472222,
    "decimalLatitude": -16.044722,
    "stateProvince": "Bahia",
    "year": 2005,
    "month": 12,
    "day": 27,
    "eventDate": "2005-12-27T00:00:00.000+0000",
    "issues": [
      "GEODETIC_DATUM_ASSUMED_WGS84"
    ],
    "lastInterpreted": "2018-09-25T15:14:28.557+0000",
    "license": "http://creativecommons.org/licenses/by-nc/4.0/legalcode",
    "identifiers": [],
    "facts": [],
    "relations": [],
    "geodeticDatum": "WGS84",
    "class": "Magnoliopsida",
    "countryCode": "BR",
    "country": "Brazil",
    "rightsHolder": "UESC - Herb\u00e1rio Universidade Estadual de Santa Cruz",
    "identifier": "BRA:UESC:UESC:0000013685",
    "recordNumber": "1423",
    "datasetName": "UESC - Herb\u00e1rio Universidade Estadual de Santa Cruz",
    "municipality": "Santo Ant\u00f4nio",
    "gbifID": "1094175434",
    "language": "pt",
    "collectionCode": "UESC",
    "occurrenceID": "BRA:UESC:UESC:0000013685",
    "type": "Collection",
    "catalogNumber": "13685",
    "recordedBy": "Nunes, T.S.",
    "institutionCode": "UESC",
    "ownerInstitutionCode": "Universidade Estadual de Santa Cruz (UESC)",
    "occurrenceRemarks": "Mata; Subarbusto ca. 1m altura.; DNA.",
    "_datasetKey": {
      "title": "UESC - Herb\u00e1rio Universidade Estadual de Santa Cruz"
    },
    "_publishingOrgKey": {
      "title": "Universidade Estadual de Santa Cruz"
    },
    "_verbatimRecord": {
      "http://rs.tdwg.org/dwc/terms/scientificName": "Heliotropium elongatum"
    }
  },
  {
    "key": 1086978319,
    "datasetKey": "aefe4840-ce1f-4b7b-b83b-1a0203e9e5e4",
    "publishingOrgKey": "3b3975ee-23fb-4943-a00e-4d6e6115b194",
    "networkKeys": [],
    "installationKey": "b38ff2b7-c8af-454e-b5af-ee760f0d5bca",
    "publishingCountry": "BR",
    "protocol": "DWC_ARCHIVE",
    "lastCrawled": "2018-09-24T16:37:42.591+0000",
    "lastParsed": "2017-12-29T14:11:39.224+0000",
    "crawlId": 114,
    "extensions": {},
    "basisOfRecord": "PRESERVED_SPECIMEN",
    "taxonKey": 7461943,
    "kingdomKey": 6,
    "phylumKey": 7707728,
    "classKey": 220,
    "orderKey": 7226464,
    "familyKey": 4930387,
    "genusKey": 2925766,
    "speciesKey": 7461943,
    "scientificName": "Heliotropium elongatum Willd. ex Cham.",
    "kingdom": "Plantae",
    "phylum": "Tracheophyta",
    "order": "Boraginales",
    "family": "Heliotropiaceae",
    "genus": "Heliotropium",
    "species": "Heliotropium elongatum",
    "genericName": "Heliotropium",
    "specificEpithet": "elongatum",
    "taxonRank": "SPECIES",
    "decimalLongitude": -42.780583,
    "decimalLatitude": -5.045361,
    "stateProvince": "Piau\u00ed",
    "year": 2004,
    "month": 1,
    "day": 31,
    "eventDate": "2004-01-31T00:00:00.000+0000",
    "issues": [
      "GEODETIC_DATUM_ASSUMED_WGS84"
    ],
    "lastInterpreted": "2018-07-07T13:00:55.235+0000",
    "license": "http://creativecommons.org/licenses/by-nc/4.0/legalcode",
    "identifiers": [],
    "facts": [],
    "relations": [],
    "geodeticDatum": "WGS84",
    "class": "Magnoliopsida",
    "countryCode": "BR",
    "country": "Brazil",
    "rightsHolder": "TEPB - Herb\u00e1rio Graziela Barroso",
    "identifier": "BRA:UFPI:TEPB:0000019628",
    "recordNumber": "69",
    "datasetName": "TEPB - Herb\u00e1rio Graziela Barroso",
    "municipality": "Teresina",
    "locality": "CCA/UFPI",
    "gbifID": "1086978319",
    "language": "pt",
    "collectionCode": "TEPB",
    "occurrenceID": "BRA:UFPI:TEPB:0000019628",
    "type": "Collection",
    "catalogNumber": "19628",
    "recordedBy": "Silva, S.C.C",
    "institutionCode": "UFPI",
    "ownerInstitutionCode": "Universidade Federal do Piau\u00ed, UFPI",
    "occurrenceRemarks": "Erva; infloresc\u00eancia com flores roxas; solo arenoso Ambiente: Mata ciliar",
    "_datasetKey": {
      "title": "TEPB - Herb\u00e1rio Graziela Barroso"
    },
    "_publishingOrgKey": {
      "title": "Universidade Federal do Piau\u00ed"
    },
    "_verbatimRecord": {
      "http://rs.tdwg.org/dwc/terms/scientificName": "Heliotropium elongatum"
    }
  },
  {
    "key": 1135919451,
    "datasetKey": "cbf8c968-37d6-45be-bf5c-e22914a384dc",
    "publishingOrgKey": "a88bec5c-1cbf-47a2-8c3e-6081804d80a5",
    "networkKeys": [],
    "installationKey": "b38ff2b7-c8af-454e-b5af-ee760f0d5bca",
    "publishingCountry": "BR",
    "protocol": "DWC_ARCHIVE",
    "lastCrawled": "2018-10-02T18:18:26.218+0000",
    "lastParsed": "2018-01-05T16:39:39.863+0000",
    "crawlId": 71,
    "extensions": {},
    "basisOfRecord": "PRESERVED_SPECIMEN",
    "taxonKey": 7461943,
    "kingdomKey": 6,
    "phylumKey": 7707728,
    "classKey": 220,
    "orderKey": 7226464,
    "familyKey": 4930387,
    "genusKey": 2925766,
    "speciesKey": 7461943,
    "scientificName": "Heliotropium elongatum Willd. ex Cham.",
    "kingdom": "Plantae",
    "phylum": "Tracheophyta",
    "order": "Boraginales",
    "family": "Heliotropiaceae",
    "genus": "Heliotropium",
    "species": "Heliotropium elongatum",
    "genericName": "Heliotropium",
    "specificEpithet": "elongatum",
    "taxonRank": "SPECIES",
    "dateIdentified": "2005-01-01T00:00:00.000+0000",
    "stateProvince": "Bahia",
    "year": 2004,
    "month": 10,
    "day": 10,
    "eventDate": "2004-10-10T00:00:00.000+0000",
    "issues": [
      "IDENTIFIED_DATE_UNLIKELY"
    ],
    "lastInterpreted": "2018-07-07T01:40:49.967+0000",
    "license": "http://creativecommons.org/licenses/by-nc/4.0/legalcode",
    "identifiers": [],
    "facts": [],
    "relations": [],
    "class": "Magnoliopsida",
    "countryCode": "BR",
    "country": "Brazil",
    "rightsHolder": "ESA - Herb\u00e1rio da Escola Superior de Agricultura Luiz de Queiroz",
    "identifier": "BRA:ESALQ:ESA:0ESA098333",
    "recordNumber": "9647",
    "datasetName": "ESA - Herb\u00e1rio da Escola Superior de Agricultura Luiz de Queiroz",
    "municipality": "Casa Nova",
    "gbifID": "1135919451",
    "language": "pt",
    "collectionCode": "ESA",
    "occurrenceID": "BRA:ESALQ:ESA:0ESA098333",
    "type": "Collection",
    "catalogNumber": "ESA098333",
    "recordedBy": "Queiroz, L.P.",
    "institutionCode": "Escola Superior de Agricultura Luiz de Queiroz, ESALQ",
    "ownerInstitutionCode": "Escola Superior de Agricultura Luiz de Queiroz, ESALQ",
    "identifiedBy": "Concei\u00e7\u00e3o, S.F.",
    "_datasetKey": {
      "title": "ESA - Herb\u00e1rio da Escola Superior de Agricultura Luiz de Queiroz"
    },
    "_publishingOrgKey": {
      "title": "Escola Superior de Agricultura Luiz de Queiroz"
    },
    "_verbatimRecord": {
      "http://rs.tdwg.org/dwc/terms/scientificName": "Heliotropium elongatum"
    }
  },
  {
    "key": 1098503677,
    "datasetKey": "f70fdd5a-e761-43b6-a854-462826cc7933",
    "publishingOrgKey": "92bd7d31-3255-4f1c-8552-cbb6fbe60478",
    "networkKeys": [],
    "installationKey": "b38ff2b7-c8af-454e-b5af-ee760f0d5bca",
    "publishingCountry": "BR",
    "protocol": "DWC_ARCHIVE",
    "lastCrawled": "2018-10-02T19:47:15.880+0000",
    "lastParsed": "2018-07-04T19:42:47.384+0000",
    "crawlId": 102,
    "extensions": {},
    "basisOfRecord": "PRESERVED_SPECIMEN",
    "taxonKey": 7461943,
    "kingdomKey": 6,
    "phylumKey": 7707728,
    "classKey": 220,
    "orderKey": 7226464,
    "familyKey": 4930387,
    "genusKey": 2925766,
    "speciesKey": 7461943,
    "scientificName": "Heliotropium elongatum Willd. ex Cham.",
    "kingdom": "Plantae",
    "phylum": "Tracheophyta",
    "order": "Boraginales",
    "family": "Heliotropiaceae",
    "genus": "Heliotropium",
    "species": "Heliotropium elongatum",
    "genericName": "Heliotropium",
    "specificEpithet": "elongatum",
    "taxonRank": "SPECIES",
    "continent": "SOUTH_AMERICA",
    "stateProvince": "S\u00e3o Paulo",
    "year": 1995,
    "month": 9,
    "day": 7,
    "eventDate": "1995-09-07T00:00:00.000+0000",
    "issues": [],
    "lastInterpreted": "2018-07-07T09:19:46.135+0000",
    "license": "http://creativecommons.org/licenses/by-nc/4.0/legalcode",
    "identifiers": [],
    "facts": [],
    "relations": [],
    "class": "Magnoliopsida",
    "countryCode": "BR",
    "country": "Brazil",
    "rightsHolder": "SJRP - Herb\u00e1rio de S\u00e3o Jos\u00e9 do Rio Preto",
    "identifier": "BRA:UNESPSJRP:SJRP:0000031523",
    "recordNumber": "2101",
    "datasetName": "SJRP - Herb\u00e1rio de S\u00e3o Jos\u00e9 do Rio Preto",
    "municipality": "Dracena",
    "gbifID": "1098503677",
    "language": "pt",
    "collectionCode": "SJRP",
    "occurrenceID": "BRA:UNESPSJRP:SJRP:0000031523",
    "type": "Collection",
    "catalogNumber": "31523",
    "recordedBy": "Bernacci, L.C.",
    "institutionCode": "UNESPSJRP",
    "ownerInstitutionCode": "Universidade Estadual Paulista, UNESP",
    "occurrenceRemarks": "Geografia: Erva, ca. 0,3m alt.;",
    "_datasetKey": {
      "title": "SJRP - Herb\u00e1rio de S\u00e3o Jos\u00e9 do Rio Preto"
    },
    "_publishingOrgKey": {
      "title": "Universidade Estadual Paulista - S\u00e3o Jos\u00e9 do Rio Preto"
    },
    "_verbatimRecord": {
      "http://rs.tdwg.org/dwc/terms/scientificName": "Heliotropium elongatum"
    }
  },
  {
    "key": 1098495262,
    "datasetKey": "f70fdd5a-e761-43b6-a854-462826cc7933",
    "publishingOrgKey": "92bd7d31-3255-4f1c-8552-cbb6fbe60478",
    "networkKeys": [],
    "installationKey": "b38ff2b7-c8af-454e-b5af-ee760f0d5bca",
    "publishingCountry": "BR",
    "protocol": "DWC_ARCHIVE",
    "lastCrawled": "2018-10-02T19:47:12.014+0000",
    "lastParsed": "2018-07-04T19:42:45.078+0000",
    "crawlId": 102,
    "extensions": {},
    "basisOfRecord": "PRESERVED_SPECIMEN",
    "taxonKey": 7461943,
    "kingdomKey": 6,
    "phylumKey": 7707728,
    "classKey": 220,
    "orderKey": 7226464,
    "familyKey": 4930387,
    "genusKey": 2925766,
    "speciesKey": 7461943,
    "scientificName": "Heliotropium elongatum Willd. ex Cham.",
    "kingdom": "Plantae",
    "phylum": "Tracheophyta",
    "order": "Boraginales",
    "family": "Heliotropiaceae",
    "genus": "Heliotropium",
    "species": "Heliotropium elongatum",
    "genericName": "Heliotropium",
    "specificEpithet": "elongatum",
    "taxonRank": "SPECIES",
    "decimalLongitude": -47.663056,
    "decimalLatitude": -22.579722,
    "continent": "SOUTH_AMERICA",
    "stateProvince": "S\u00e3o Paulo",
    "year": 1994,
    "month": 2,
    "day": 1,
    "eventDate": "1994-02-01T00:00:00.000+0000",
    "issues": [
      "GEODETIC_DATUM_ASSUMED_WGS84"
    ],
    "lastInterpreted": "2018-07-07T09:19:46.101+0000",
    "license": "http://creativecommons.org/licenses/by-nc/4.0/legalcode",
    "identifiers": [],
    "facts": [],
    "relations": [],
    "geodeticDatum": "WGS84",
    "class": "Magnoliopsida",
    "countryCode": "BR",
    "country": "Brazil",
    "rightsHolder": "SJRP - Herb\u00e1rio de S\u00e3o Jos\u00e9 do Rio Preto",
    "identifier": "BRA:UNESPSJRP:SJRP:0000017653",
    "recordNumber": "1936",
    "datasetName": "SJRP - Herb\u00e1rio de S\u00e3o Jos\u00e9 do Rio Preto",
    "municipality": "Charqueada",
    "locality": "Usina Costa Pinto",
    "gbifID": "1098495262",
    "language": "pt",
    "collectionCode": "SJRP",
    "occurrenceID": "BRA:UNESPSJRP:SJRP:0000017653",
    "type": "Collection",
    "catalogNumber": "17653",
    "recordedBy": "Barreto, K.D.",
    "institutionCode": "UNESPSJRP",
    "ownerInstitutionCode": "Universidade Estadual Paulista, UNESP",
    "occurrenceRemarks": "Geografia: erva, 40cm alt.;",
    "_datasetKey": {
      "title": "SJRP - Herb\u00e1rio de S\u00e3o Jos\u00e9 do Rio Preto"
    },
    "_publishingOrgKey": {
      "title": "Universidade Estadual Paulista - S\u00e3o Jos\u00e9 do Rio Preto"
    },
    "_verbatimRecord": {
      "http://rs.tdwg.org/dwc/terms/scientificName": "Heliotropium elongatum"
    }
  },
  {
    "key": 1135851290,
    "datasetKey": "cbf8c968-37d6-45be-bf5c-e22914a384dc",
    "publishingOrgKey": "a88bec5c-1cbf-47a2-8c3e-6081804d80a5",
    "networkKeys": [],
    "installationKey": "b38ff2b7-c8af-454e-b5af-ee760f0d5bca",
    "publishingCountry": "BR",
    "protocol": "DWC_ARCHIVE",
    "lastCrawled": "2018-10-02T18:15:32.649+0000",
    "lastParsed": "2018-01-05T16:39:10.982+0000",
    "crawlId": 71,
    "extensions": {},
    "basisOfRecord": "PRESERVED_SPECIMEN",
    "taxonKey": 7461943,
    "kingdomKey": 6,
    "phylumKey": 7707728,
    "classKey": 220,
    "orderKey": 7226464,
    "familyKey": 4930387,
    "genusKey": 2925766,
    "speciesKey": 7461943,
    "scientificName": "Heliotropium elongatum Willd. ex Cham.",
    "kingdom": "Plantae",
    "phylum": "Tracheophyta",
    "order": "Boraginales",
    "family": "Heliotropiaceae",
    "genus": "Heliotropium",
    "species": "Heliotropium elongatum",
    "genericName": "Heliotropium",
    "specificEpithet": "elongatum",
    "taxonRank": "SPECIES",
    "dateIdentified": "2006-09-01T00:00:00.000+0000",
    "stateProvince": "S\u00e3o Paulo",
    "year": 1994,
    "month": 2,
    "day": 1,
    "eventDate": "1994-02-01T00:00:00.000+0000",
    "issues": [
      "IDENTIFIED_DATE_UNLIKELY"
    ],
    "lastInterpreted": "2018-07-07T01:40:49.967+0000",
    "license": "http://creativecommons.org/licenses/by-nc/4.0/legalcode",
    "identifiers": [],
    "facts": [],
    "relations": [],
    "class": "Magnoliopsida",
    "countryCode": "BR",
    "country": "Brazil",
    "rightsHolder": "ESA - Herb\u00e1rio da Escola Superior de Agricultura Luiz de Queiroz",
    "identifier": "BRA:ESALQ:ESA:0ESA023204",
    "recordNumber": "1936",
    "datasetName": "ESA - Herb\u00e1rio da Escola Superior de Agricultura Luiz de Queiroz",
    "municipality": "Charqueada",
    "locality": "Usina Costa Pinto (ponte). Pasto.",
    "gbifID": "1135851290",
    "language": "pt",
    "collectionCode": "ESA",
    "occurrenceID": "BRA:ESALQ:ESA:0ESA023204",
    "type": "Collection",
    "catalogNumber": "ESA023204",
    "recordedBy": "Barreto, K.D.; Fernandes, G.D.; Vitti, F.X.",
    "institutionCode": "Escola Superior de Agricultura Luiz de Queiroz, ESALQ",
    "ownerInstitutionCode": "Escola Superior de Agricultura Luiz de Queiroz, ESALQ",
    "identifiedBy": "Melo, J.I.M.",
    "_datasetKey": {
      "title": "ESA - Herb\u00e1rio da Escola Superior de Agricultura Luiz de Queiroz"
    },
    "_publishingOrgKey": {
      "title": "Escola Superior de Agricultura Luiz de Queiroz"
    },
    "_verbatimRecord": {
      "http://rs.tdwg.org/dwc/terms/scientificName": "Heliotropium elongatum"
    }
  },
  {
    "key": 1098503696,
    "datasetKey": "f70fdd5a-e761-43b6-a854-462826cc7933",
    "publishingOrgKey": "92bd7d31-3255-4f1c-8552-cbb6fbe60478",
    "networkKeys": [],
    "installationKey": "b38ff2b7-c8af-454e-b5af-ee760f0d5bca",
    "publishingCountry": "BR",
    "protocol": "DWC_ARCHIVE",
    "lastCrawled": "2018-10-02T19:47:15.867+0000",
    "lastParsed": "2018-07-04T19:42:47.383+0000",
    "crawlId": 102,
    "extensions": {},
    "basisOfRecord": "PRESERVED_SPECIMEN",
    "taxonKey": 7461943,
    "kingdomKey": 6,
    "phylumKey": 7707728,
    "classKey": 220,
    "orderKey": 7226464,
    "familyKey": 4930387,
    "genusKey": 2925766,
    "speciesKey": 7461943,
    "scientificName": "Heliotropium elongatum Willd. ex Cham.",
    "kingdom": "Plantae",
    "phylum": "Tracheophyta",
    "order": "Boraginales",
    "family": "Heliotropiaceae",
    "genus": "Heliotropium",
    "species": "Heliotropium elongatum",
    "genericName": "Heliotropium",
    "specificEpithet": "elongatum",
    "taxonRank": "SPECIES",
    "continent": "SOUTH_AMERICA",
    "stateProvince": "S\u00e3o Paulo",
    "year": 1994,
    "month": 11,
    "day": 9,
    "eventDate": "1994-11-09T00:00:00.000+0000",
    "issues": [],
    "lastInterpreted": "2018-07-07T09:19:46.270+0000",
    "license": "http://creativecommons.org/licenses/by-nc/4.0/legalcode",
    "identifiers": [],
    "facts": [],
    "relations": [],
    "class": "Magnoliopsida",
    "countryCode": "BR",
    "country": "Brazil",
    "rightsHolder": "SJRP - Herb\u00e1rio de S\u00e3o Jos\u00e9 do Rio Preto",
    "identifier": "BRA:UNESPSJRP:SJRP:0000031524",
    "recordNumber": "s/n",
    "datasetName": "SJRP - Herb\u00e1rio de S\u00e3o Jos\u00e9 do Rio Preto",
    "municipality": "C\u00e1ssia dos Coqueiros",
    "gbifID": "1098503696",
    "language": "pt",
    "collectionCode": "SJRP",
    "occurrenceID": "BRA:UNESPSJRP:SJRP:0000031524",
    "type": "Collection",
    "catalogNumber": "31524",
    "recordedBy": "Tozzi, A.M.G.A.",
    "institutionCode": "UNESPSJRP",
    "ownerInstitutionCode": "Universidade Estadual Paulista, UNESP",
    "occurrenceRemarks": "Geografia: herb\u00e1cea, 0,3m, flores lilases;",
    "_datasetKey": {
      "title": "SJRP - Herb\u00e1rio de S\u00e3o Jos\u00e9 do Rio Preto"
    },
    "_publishingOrgKey": {
      "title": "Universidade Estadual Paulista - S\u00e3o Jos\u00e9 do Rio Preto"
    },
    "_verbatimRecord": {
      "http://rs.tdwg.org/dwc/terms/scientificName": "Heliotropium elongatum"
    }
  },
  {
    "key": 1098503678,
    "datasetKey": "f70fdd5a-e761-43b6-a854-462826cc7933",
    "publishingOrgKey": "92bd7d31-3255-4f1c-8552-cbb6fbe60478",
    "networkKeys": [],
    "installationKey": "b38ff2b7-c8af-454e-b5af-ee760f0d5bca",
    "publishingCountry": "BR",
    "protocol": "DWC_ARCHIVE",
    "lastCrawled": "2018-10-02T19:47:15.810+0000",
    "lastParsed": "2018-07-04T19:42:47.426+0000",
    "crawlId": 102,
    "extensions": {},
    "basisOfRecord": "PRESERVED_SPECIMEN",
    "taxonKey": 7461943,
    "kingdomKey": 6,
    "phylumKey": 7707728,
    "classKey": 220,
    "orderKey": 7226464,
    "familyKey": 4930387,
    "genusKey": 2925766,
    "speciesKey": 7461943,
    "scientificName": "Heliotropium elongatum Willd. ex Cham.",
    "kingdom": "Plantae",
    "phylum": "Tracheophyta",
    "order": "Boraginales",
    "family": "Heliotropiaceae",
    "genus": "Heliotropium",
    "species": "Heliotropium elongatum",
    "genericName": "Heliotropium",
    "specificEpithet": "elongatum",
    "taxonRank": "SPECIES",
    "continent": "SOUTH_AMERICA",
    "stateProvince": "S\u00e3o Paulo",
    "year": 1994,
    "month": 11,
    "day": 11,
    "eventDate": "1994-11-11T00:00:00.000+0000",
    "issues": [],
    "lastInterpreted": "2018-07-07T09:19:46.252+0000",
    "license": "http://creativecommons.org/licenses/by-nc/4.0/legalcode",
    "identifiers": [],
    "facts": [],
    "relations": [],
    "class": "Magnoliopsida",
    "countryCode": "BR",
    "country": "Brazil",
    "rightsHolder": "SJRP - Herb\u00e1rio de S\u00e3o Jos\u00e9 do Rio Preto",
    "identifier": "BRA:UNESPSJRP:SJRP:0000031525",
    "recordNumber": "s/n",
    "datasetName": "SJRP - Herb\u00e1rio de S\u00e3o Jos\u00e9 do Rio Preto",
    "municipality": "Itobi",
    "gbifID": "1098503678",
    "language": "pt",
    "collectionCode": "SJRP",
    "occurrenceID": "BRA:UNESPSJRP:SJRP:0000031525",
    "type": "Collection",
    "catalogNumber": "31525",
    "recordedBy": "Tozzi, A.M.G.A.",
    "institutionCode": "UNESPSJRP",
    "ownerInstitutionCode": "Universidade Estadual Paulista, UNESP",
    "occurrenceRemarks": "Geografia: herb\u00e1cea, 0,4m, corola lil\u00e1s.;",
    "_datasetKey": {
      "title": "SJRP - Herb\u00e1rio de S\u00e3o Jos\u00e9 do Rio Preto"
    },
    "_publishingOrgKey": {
      "title": "Universidade Estadual Paulista - S\u00e3o Jos\u00e9 do Rio Preto"
    },
    "_verbatimRecord": {
      "http://rs.tdwg.org/dwc/terms/scientificName": "Heliotropium elongatum"
    }
  },
  {
    "key": 1098495050,
    "datasetKey": "f70fdd5a-e761-43b6-a854-462826cc7933",
    "publishingOrgKey": "92bd7d31-3255-4f1c-8552-cbb6fbe60478",
    "networkKeys": [],
    "installationKey": "b38ff2b7-c8af-454e-b5af-ee760f0d5bca",
    "publishingCountry": "BR",
    "protocol": "DWC_ARCHIVE",
    "lastCrawled": "2018-10-02T19:47:11.897+0000",
    "lastParsed": "2018-07-04T19:42:44.970+0000",
    "crawlId": 102,
    "extensions": {},
    "basisOfRecord": "PRESERVED_SPECIMEN",
    "taxonKey": 7461943,
    "kingdomKey": 6,
    "phylumKey": 7707728,
    "classKey": 220,
    "orderKey": 7226464,
    "familyKey": 4930387,
    "genusKey": 2925766,
    "speciesKey": 7461943,
    "scientificName": "Heliotropium elongatum Willd. ex Cham.",
    "kingdom": "Plantae",
    "phylum": "Tracheophyta",
    "order": "Boraginales",
    "family": "Heliotropiaceae",
    "genus": "Heliotropium",
    "species": "Heliotropium elongatum",
    "genericName": "Heliotropium",
    "specificEpithet": "elongatum",
    "taxonRank": "SPECIES",
    "continent": "SOUTH_AMERICA",
    "stateProvince": "S\u00e3o Paulo",
    "year": 1978,
    "month": 11,
    "day": 30,
    "eventDate": "1978-11-30T00:00:00.000+0000",
    "issues": [],
    "lastInterpreted": "2018-07-07T09:19:46.252+0000",
    "license": "http://creativecommons.org/licenses/by-nc/4.0/legalcode",
    "identifiers": [],
    "facts": [],
    "relations": [],
    "class": "Magnoliopsida",
    "countryCode": "BR",
    "country": "Brazil",
    "rightsHolder": "SJRP - Herb\u00e1rio de S\u00e3o Jos\u00e9 do Rio Preto",
    "identifier": "BRA:UNESPSJRP:SJRP:0000017410",
    "recordNumber": "s/n",
    "datasetName": "SJRP - Herb\u00e1rio de S\u00e3o Jos\u00e9 do Rio Preto",
    "municipality": "Porto Feliz",
    "gbifID": "1098495050",
    "language": "pt",
    "collectionCode": "SJRP",
    "occurrenceID": "BRA:UNESPSJRP:SJRP:0000017410",
    "type": "Collection",
    "catalogNumber": "17410",
    "recordedBy": "Cardelli, M.A.",
    "institutionCode": "UNESPSJRP",
    "ownerInstitutionCode": "Universidade Estadual Paulista, UNESP",
    "_datasetKey": {
      "title": "SJRP - Herb\u00e1rio de S\u00e3o Jos\u00e9 do Rio Preto"
    },
    "_publishingOrgKey": {
      "title": "Universidade Estadual Paulista - S\u00e3o Jos\u00e9 do Rio Preto"
    },
    "_verbatimRecord": {
      "http://rs.tdwg.org/dwc/terms/scientificName": "Heliotropium elongatum"
    }
  },
  {
    "key": 1086970102,
    "datasetKey": "aefe4840-ce1f-4b7b-b83b-1a0203e9e5e4",
    "publishingOrgKey": "3b3975ee-23fb-4943-a00e-4d6e6115b194",
    "networkKeys": [],
    "installationKey": "b38ff2b7-c8af-454e-b5af-ee760f0d5bca",
    "publishingCountry": "BR",
    "protocol": "DWC_ARCHIVE",
    "lastCrawled": "2018-09-24T16:37:38.678+0000",
    "lastParsed": "2017-12-29T14:11:36.023+0000",
    "crawlId": 114,
    "extensions": {},
    "basisOfRecord": "PRESERVED_SPECIMEN",
    "taxonKey": 7461943,
    "kingdomKey": 6,
    "phylumKey": 7707728,
    "classKey": 220,
    "orderKey": 7226464,
    "familyKey": 4930387,
    "genusKey": 2925766,
    "speciesKey": 7461943,
    "scientificName": "Heliotropium elongatum Willd. ex Cham.",
    "kingdom": "Plantae",
    "phylum": "Tracheophyta",
    "order": "Boraginales",
    "family": "Heliotropiaceae",
    "genus": "Heliotropium",
    "species": "Heliotropium elongatum",
    "genericName": "Heliotropium",
    "specificEpithet": "elongatum",
    "taxonRank": "SPECIES",
    "dateIdentified": "1985-05-16T00:00:00.000+0000",
    "stateProvince": "Piau\u00ed",
    "year": 1978,
    "month": 12,
    "day": 16,
    "eventDate": "1978-12-16T00:00:00.000+0000",
    "issues": [],
    "lastInterpreted": "2018-07-07T13:00:55.186+0000",
    "license": "http://creativecommons.org/licenses/by-nc/4.0/legalcode",
    "identifiers": [],
    "facts": [],
    "relations": [],
    "class": "Magnoliopsida",
    "countryCode": "BR",
    "country": "Brazil",
    "rightsHolder": "TEPB - Herb\u00e1rio Graziela Barroso",
    "identifier": "BRA:UFPI:TEPB:0000000320",
    "datasetName": "TEPB - Herb\u00e1rio Graziela Barroso",
    "municipality": "S\u00e3o Raimundo Nonato",
    "locality": "Serra da Capivara",
    "gbifID": "1086970102",
    "language": "pt",
    "collectionCode": "TEPB",
    "occurrenceID": "BRA:UFPI:TEPB:0000000320",
    "type": "Collection",
    "catalogNumber": "320",
    "recordedBy": "Freire, F. M. T.",
    "institutionCode": "UFPI",
    "ownerInstitutionCode": "Universidade Federal do Piau\u00ed, UFPI",
    "occurrenceRemarks": "dwc_commonname: Crista-de-galo",
    "identifiedBy": "F. M. T. Freire",
    "_datasetKey": {
      "title": "TEPB - Herb\u00e1rio Graziela Barroso"
    },
    "_publishingOrgKey": {
      "title": "Universidade Federal do Piau\u00ed"
    },
    "_verbatimRecord": {
      "http://rs.tdwg.org/dwc/terms/scientificName": "Heliotropium elongatum"
    }
  },
  {
    "key": 239348984,
    "datasetKey": "84c1fa90-f762-11e1-a439-00145eb45e9a",
    "publishingOrgKey": "edd92410-ac77-11de-90e0-b8a03c50a862",
    "networkKeys": [],
    "installationKey": "601aa750-f762-11e1-a439-00145eb45e9a",
    "publishingCountry": "US",
    "protocol": "DWC_ARCHIVE",
    "lastCrawled": "2018-02-28T18:29:14.680+0000",
    "lastParsed": "2018-02-28T18:37:18.237+0000",
    "crawlId": 43,
    "extensions": {},
    "basisOfRecord": "PRESERVED_SPECIMEN",
    "taxonKey": 7461943,
    "kingdomKey": 6,
    "phylumKey": 7707728,
    "classKey": 220,
    "orderKey": 7226464,
    "familyKey": 4930387,
    "genusKey": 2925766,
    "speciesKey": 7461943,
    "scientificName": "Heliotropium elongatum Willd. ex Cham.",
    "kingdom": "Plantae",
    "phylum": "Tracheophyta",
    "order": "Boraginales",
    "family": "Heliotropiaceae",
    "genus": "Heliotropium",
    "species": "Heliotropium elongatum",
    "genericName": "Heliotropium",
    "specificEpithet": "elongatum",
    "taxonRank": "SPECIES",
    "year": 1976,
    "month": 10,
    "day": 11,
    "eventDate": "1976-10-11T00:00:00.000+0000",
    "issues": [],
    "lastInterpreted": "2018-07-07T02:00:55.563+0000",
    "license": "http://creativecommons.org/licenses/by/4.0/legalcode",
    "identifiers": [],
    "facts": [],
    "relations": [],
    "class": "Magnoliopsida",
    "countryCode": "BR",
    "country": "Brazil",
    "identifier": "239348984",
    "recordedBy": "G. Hatschbach",
    "catalogNumber": "229853",
    "institutionCode": "ASU",
    "locality": "Rod. BR-020, 25km S de Alvorada do Norte, Goi\u00e1s",
    "gbifID": "239348984",
    "collectionCode": "ASUPlants",
    "_datasetKey": {
      "title": "Arizona State University Vascular Plant Herbarium"
    },
    "_publishingOrgKey": {
      "title": "Arizona State University, Global Institute for Sustainability"
    },
    "_verbatimRecord": {
      "http://rs.tdwg.org/dwc/terms/scientificName": "Heliotropium elongatum"
    }
  },
  {
    "key": 1228604281,
    "datasetKey": "90c853e6-56bd-480b-8e8f-6285c3f8d42b",
    "publishingOrgKey": "7b8aff00-a9f8-11d8-944b-b8a03c50a862",
    "networkKeys": [],
    "installationKey": "3b84ff5b-79ce-427c-acb7-b4004e160f66",
    "publishingCountry": "US",
    "protocol": "DWC_ARCHIVE",
    "lastCrawled": "2018-06-01T19:15:13.812+0000",
    "lastParsed": "2018-06-01T19:16:16.342+0000",
    "crawlId": 76,
    "extensions": {},
    "basisOfRecord": "PRESERVED_SPECIMEN",
    "taxonKey": 9212972,
    "kingdomKey": 6,
    "phylumKey": 7707728,
    "classKey": 220,
    "orderKey": 7226464,
    "familyKey": 4930387,
    "genusKey": 2925766,
    "speciesKey": 7461943,
    "scientificName": "Heliotropium elongatum var. hispidum Fresen.",
    "kingdom": "Plantae",
    "phylum": "Tracheophyta",
    "order": "Boraginales",
    "family": "Heliotropiaceae",
    "genus": "Heliotropium",
    "species": "Heliotropium elongatum",
    "genericName": "Heliotropium",
    "specificEpithet": "elongatum",
    "infraspecificEpithet": "hispidum",
    "taxonRank": "VARIETY",
    "decimalLongitude": -52.8731,
    "decimalLatitude": -10.8339,
    "continent": "SOUTH_AMERICA",
    "typeStatus": "TYPE",
    "issues": [
      "GEODETIC_DATUM_ASSUMED_WGS84"
    ],
    "lastInterpreted": "2018-07-06T20:48:58.657+0000",
    "license": "http://creativecommons.org/publicdomain/zero/1.0/legalcode",
    "identifiers": [],
    "media": [
      {
        "type": "StillImage",
        "format": "image/jpeg",
        "identifier": "http://fm-digital-assets.fieldmuseum.org/287/476/20308.jpg",
        "title": "20308",
        "description": "Field Museum photo negatives collection; M\ufffdnchen specimen of Heliotropium elongatum var. hispidum Fresen., BRAZIL, C. F. P. Martius, Type [status unknown], M",
        "creator": "Field Museum of Natural History - Botany Department",
        "license": "(c) The Field Museum"
      }
    ],
    "facts": [],
    "relations": [],
    "geodeticDatum": "WGS84",
    "class": "Magnoliopsida",
    "countryCode": "BR",
    "country": "Brazil",
    "rightsHolder": "The Field Museum of Natural History",
    "identifier": "bb1eec4f-2d44-4748-8963-79bb78de8dd5",
    "nomenclaturalCode": "ICBN",
    "institutionID": "F",
    "higherGeography": "South America, BRAZIL",
    "gbifID": "1228604281",
    "language": "en",
    "collectionCode": "Botany",
    "occurrenceID": "bb1eec4f-2d44-4748-8963-79bb78de8dd5",
    "type": "PhysicalObject",
    "recordedBy": "C. F. P. Martius",
    "organismID": "217001",
    "institutionCode": "F",
    "ownerInstitutionCode": "F",
    "datasetID": "seeds-01-june-2018",
    "accessRights": "http://fieldmuseum.org/about/copyright-information",
    "higherClassification": "Plantae Spermatophyta Dicotyledoneae Boraginaceae",
    "collectionID": "Botany",
    "_datasetKey": {
      "title": "Field Museum of Natural History (Botany)  Seed Plant Collection"
    },
    "_publishingOrgKey": {
      "title": "Field Museum"
    },
    "_verbatimRecord": {
      "http://rs.tdwg.org/dwc/terms/scientificName": "Heliotropium elongatum var. hispidum Fresen."
    }
  }
]